webhunter/__init__.py
webhunter/websniffer.py
webhunter-0.0.1.dist-info/METADATA
webhunter-0.0.1.dist-info/WHEEL
webhunter-0.0.1.dist-info/top_level.txt
webhunter-0.0.1.dist-info/RECORD
