Metadata-Version: 2.1
Name: webhunter
Version: 0.0.1
Summary: webhunter
Home-page: https://github.com/xuzhiyu1995/webhunter
Author: xuzhiyu
Author-email: GloryOfAll1994@gmail.com
License: UNKNOWN
Platform: UNKNOWN
Requires-Python: >=3.6
